[
  {
    "keyword": "phone",
    "icon": "./img/svg/phone.svg",
    "text": "+33 6 23 39 79 78",
    "link": "tel:+33623397978"
  },
  {
    "keyword": "mail",
    "icon": "./img/svg/mail.svg",
    "text": "tboittin@gmail.com",
    "link": "mailto:tboittin@gmaiil.com"
  },
  {
    "keyword": "domain",
    "icon": "./img/svg/globe.svg",
    "text": "thomasboittin.com",
    "link": "https://thomasboittin.com/"
  },
  {
    "keyword": "location",
    "icon": "./img/svg/placeholder.svg",
    "text": "6, boulevard Georges Clemenceau, Draguignan, France"
  }
]
